datateer_cli/__init__.py
datateer_cli/cli.py
datateer_cli/cli_old.py
datateer_cli/commands/config/commands.py
datateer_cli/commands/config/operations.py
datateer_cli/commands/datalake/commands.py
datateer_cli/commands/docs/commands.py
datateer_cli/commands/docs/docs.py
datateer_cli/commands/docs/generate_erd.py
datateer_cli/commands/echo/echo_commands.py
datateer_cli/commands/infra/commands.py
datateer_cli/commands/infra/terraform_util.py
datateer_cli/commands/pipeline/aws_deploy_flow.py
datateer_cli/commands/pipeline/commands.py
datateer_cli/commands/pipeline/deploy_flow.py
datateer_cli/commands/pipeline/flow/.dockerignore
datateer_cli/commands/pipeline/flow/Dockerfile
datateer_cli/commands/pipeline/flow/Dockerfile.gcp
datateer_cli/commands/pipeline/gcp_deploy_flow.py
datateer_cli/developer_setup.py
datateer_cli/docker_util.py
datateer_cli/install_bfg.sh
datateer_cli/logging.py
datateer_cli/orchestration/pipeline_test.py
datateer_cli/prefect_ops.py
datateer_cli/security_scan_no_forbidden_files.py
datateer_cli/ssh/datateer-machine-key
datateer_cli/ssh/datateer-machine-key.pub
datateer_cli/ssh/readme
datateer_cli-1.1.0.dist-info/METADATA
datateer_cli-1.1.0.dist-info/WHEEL
datateer_cli-1.1.0.dist-info/entry_points.txt
datateer_cli-1.1.0.dist-info/RECORD
