Metadata-Version: 2.3
Name: datateer-cli
Version: 1.1.0
Summary: Datateer CLI to support devops and infrastructure
Author: Datateer
Author-email: dev@datateer.com
Requires-Python: >=3.9,<4.0
Classifier: Programming Language :: Python :: 3
Classifier: Programming Language :: Python :: 3.9
Classifier: Programming Language :: Python :: 3.10
Classifier: Programming Language :: Python :: 3.11
Classifier: Programming Language :: Python :: 3.12
Classifier: Programming Language :: Python :: 3.13
Provides-Extra: visualization
Requires-Dist: PyYAML (>6.0.0)
Requires-Dist: boto3 (>=1.24.46,<2.0.0)
Requires-Dist: certifi (==2025.1.31)
Requires-Dist: click (>=7.0)
Requires-Dist: erd-python (>=0.6.2,<0.7.0) ; extra == "visualization"
Requires-Dist: google-cloud-storage (>=2.5.0,<3.0.0)
Requires-Dist: pathspec (>=0.9.0,<0.10.0)
Requires-Dist: pygraphviz (>=1.10,<2.0) ; extra == "visualization"
